resl/__init__.py
resl/cli.py
resl/colorful.py
resl-0.0.1.dist-info/METADATA
resl-0.0.1.dist-info/WHEEL
resl-0.0.1.dist-info/entry_points.txt
resl-0.0.1.dist-info/top_level.txt
resl-0.0.1.dist-info/RECORD
